pytest_class_fixtures/__init__.py
pytest_class_fixtures-0.1.0.dist-info/METADATA
pytest_class_fixtures-0.1.0.dist-info/WHEEL
pytest_class_fixtures-0.1.0.dist-info/RECORD
