Metadata-Version: 2.1
Name: pytest-class-fixtures
Version: 0.1.0
Summary: Class as PyTest fixtures (and BDD steps)
License: MIT
Author: EPFL ISAS-FSD team
Author-email: isas-fsd@groupes.epfl.ch
Requires-Python: >=3.8,<4.0
Classifier: License :: OSI Approved :: MIT License
Classifier: Programming Language :: Python :: 3
Classifier: Programming Language :: Python :: 3.8
Classifier: Programming Language :: Python :: 3.9
Classifier: Programming Language :: Python :: 3.10
Classifier: Programming Language :: Python :: 3.11
Classifier: Programming Language :: Python :: 3.12
Classifier: Programming Language :: Python :: 3.13
Requires-Dist: pytest (>=8.3.3,<9.0.0)
